MANIFEST.in
README.rst
setup.py
NiftyPy/Common.py
NiftyPy/__init__.py
NiftyPy.egg-info/PKG-INFO
NiftyPy.egg-info/SOURCES.txt
NiftyPy.egg-info/dependency_links.txt
NiftyPy.egg-info/requires.txt
NiftyPy.egg-info/top_level.txt
NiftyPy/NiftyRec/NiftyRec.py
NiftyPy/NiftyRec/NiftyRec_bk.py
NiftyPy/NiftyRec/__init__.py
NiftyPy/NiftyReg/NiftyReg.py
NiftyPy/NiftyReg/__init__.py
NiftyPy/NiftySeg/__init__.py
NiftyPy/test/__init__.py