Metadata-Version: 1.1
Name: NiftyPy
Version: 0.4.0
Summary: Python wrapper for NiftyRec, NiftyReg and NiftySeg: tomographic reconstruction, volumetric registration and segmentation.
Home-page: http://www.occiput.io/
Author: Stefano Pedemonte
Author-email: spedemonte@mgh.harvard.edu
License: LICENSE.txt
Keywords: Imaging,Registration,Segmentation,Medical Imaging,PET,SPECT,emission tomography,transmission tomography,tomographic reconstruction
Platform: UNKNOWN
Classifier: Programming Language :: Python
Classifier: Development Status :: 4 - Beta
Classifier: Environment :: Other Environment
Classifier: Intended Audience :: Science/Research
Classifier: License :: OSI Approved :: BSD License
Classifier: Operating System :: OS Independent
Classifier: Topic :: Scientific/Engineering :: Medical Science Apps.
Classifier: Topic :: Scientific/Engineering :: Mathematics
Classifier: Topic :: Scientific/Engineering :: Bio-Informatics
